grelmicro/__init__.py
grelmicro/errors.py
grelmicro/py.typed
grelmicro/logging/__init__.py
grelmicro/logging/config.py
grelmicro/logging/errors.py
grelmicro/logging/loguru.py
grelmicro/resilience/__init__.py
grelmicro/resilience/circuitbreaker.py
grelmicro/resilience/errors.py
grelmicro/sync/__init__.py
grelmicro/sync/_backends.py
grelmicro/sync/_base.py
grelmicro/sync/_utils.py
grelmicro/sync/abc.py
grelmicro/sync/errors.py
grelmicro/sync/leaderelection.py
grelmicro/sync/lock.py
grelmicro/sync/memory.py
grelmicro/sync/postgres.py
grelmicro/sync/redis.py
grelmicro/task/__init__.py
grelmicro/task/_interval.py
grelmicro/task/_utils.py
grelmicro/task/abc.py
grelmicro/task/errors.py
grelmicro/task/manager.py
grelmicro/task/router.py
grelmicro-0.3.1.dist-info/METADATA
grelmicro-0.3.1.dist-info/WHEEL
grelmicro-0.3.1.dist-info/licenses/LICENSE
grelmicro-0.3.1.dist-info/RECORD
