Metadata-Version: 2.4
Name: grelmicro
Version: 0.3.1
Summary: Grelmicro is a lightweight framework/toolkit for building async microservices in Python
Project-URL: Repository, https://github.com/grelinfo/grelmicro.git
Project-URL: Issues, https://github.com/grelinfo/grelmicro/issues
Author-email: Loïc Gremaud <grelinfo@gmail.com>
License-Expression: MIT
License-File: LICENSE
Classifier: Development Status :: 1 - Planning
Classifier: Environment :: Web Environment
Classifier: Framework :: AsyncIO
Classifier: Framework :: FastAPI
Classifier: Framework :: Pydantic
Classifier: Framework :: Pydantic :: 2
Classifier: Intended Audience :: Developers
Classifier: Intended Audience :: Information Technology
Classifier: Intended Audience :: System Administrators
Classifier: License :: OSI Approved :: MIT License
Classifier: Operating System :: OS Independent
Classifier: Programming Language :: Python
Classifier: Programming Language :: Python :: 3
Classifier: Programming Language :: Python :: 3 :: Only
Classifier: Programming Language :: Python :: 3.11
Classifier: Programming Language :: Python :: 3.12
Classifier: Programming Language :: Python :: 3.13
Classifier: Topic :: Internet
Classifier: Topic :: Software Development
Classifier: Topic :: Software Development :: Libraries
Classifier: Topic :: Software Development :: Libraries :: Application Frameworks
Classifier: Topic :: Software Development :: Libraries :: Python Modules
Classifier: Typing :: Typed
Requires-Python: >=3.11
Requires-Dist: anyio>=4.0.0
Requires-Dist: fast-depends>=2.0.0
Requires-Dist: pydantic-settings>=2.5.0
Requires-Dist: pydantic>=2.5.0
Provides-Extra: postgres
Requires-Dist: asyncpg>=0.30.0; extra == 'postgres'
Provides-Extra: redis
Requires-Dist: redis>=5.0.0; extra == 'redis'
Provides-Extra: standard
Requires-Dist: loguru>=0.7.2; extra == 'standard'
Requires-Dist: orjson>=3.10.11; extra == 'standard'
